pyaero/__init__.py
pyaero/calcD.py
pyaero/discretize.py
pyaero/version.py
pyaero/wing.py
pyaero_dlm-0.1.2.dist-info/LICENSE
pyaero_dlm-0.1.2.dist-info/METADATA
pyaero_dlm-0.1.2.dist-info/WHEEL
pyaero_dlm-0.1.2.dist-info/top_level.txt
pyaero_dlm-0.1.2.dist-info/RECORD
